ivyorm/__init__.py
ivyorm/config.toml
ivyorm/ivypy.egg-info/dependency_links.txt
ivyorm/ivypy.egg-info/PKG-INFO
ivyorm/ivypy.egg-info/requires.txt
ivyorm/ivypy.egg-info/SOURCES.txt
ivyorm/ivypy.egg-info/top_level.txt
ivyorm/model/test.json
ivyorm/module/__init__.py
ivyorm/module/base.py
ivyorm/module/connection/__init__.py
ivyorm/module/connection/postgres.py
ivyorm/module/connection.py
ivyorm/module/datasource.py
ivyorm/module/dictionary.py
ivyorm/module/file.py
ivyorm/module/interface/IConnection.py
ivyorm/module/util/__init__.py
ivyorm/module/util/console.py
ivyorm/module/validation.py
ivyorm/run.py
ivyorm-0.1.24.dist-info/LICENSE.txt
ivyorm-0.1.24.dist-info/METADATA
ivyorm-0.1.24.dist-info/WHEEL
ivyorm-0.1.24.dist-info/RECORD
