Metadata-Version: 2.1
Name: ivyorm
Version: 0.1.24
Summary: An ORM for Python
License: MIT
Author: James Randell
Author-email: jamesrandell@me.com
Requires-Python: >=3.11,<4.0
Classifier: License :: OSI Approved :: MIT License
Classifier: Programming Language :: Python :: 3
Classifier: Programming Language :: Python :: 3.11
